Workbook

Sheet Assumptions
A1: Progetto Valvole Italia — LBO assumptions
A2: Legend: blue = input (change freely, the LBO sheet recalculates) · black = formula · yellow = key assumption. Source: provided = stated in the description · estimated = Claude's estimate · derived = computed from other inputs · adjusted = changed by a guardrail · scenario = changed by the agent for this scenario.
A4: Assumption | B4: Value | C4: Unit | D4: Source | E4: Rationale / guardrail notes
A6: Transaction
A7: LTM revenue at closing | B7: 320 | C7: EUR mm | D7: provided | E7: Fatturato di 320 milioni di euro indicato esplicitamente nella descrizione.
A8: LTM EBITDA at closing (sizes price and debt) | B8: 44.8 | C8: EUR mm | D8: derived | E8: Calcolato come 320 milioni x 14% di margine EBITDA stimato per un produttore di valvole con componenti critiche.
A9: LTM EBITDA margin (memo) | B9: =B8/B7 | C9: % of revenue | D9: derived
A10: Entry EV / LTM EBITDA | B10: 8 | C10: x | D10: estimated | E10: Centro del range industrials (7-10x): buona nicchia tecnica ma ciclicità oil&gas e concentrazione clienti giustificano un multiplo non aggressivo.
A12: Operating plan (held flat over the projection)
A13: EBITDA margin, projection years | B13: 0.14 | C13: % of revenue | D13: estimated | E13: Parte centrale del range industrials (10-20%): valvole per oil&gas hanno contenuto tecnico e after-market, ma il mix con utilities e la concorrenza su gara limitano la marginalità.
A14: Revenue growth p.a. | B14: 0.03 | C14: % | D14: estimated | E14: Crescita moderata (3%) coerente con capex di utilities e ciclo oil&gas maturo, in linea con il range industrials 2-6%.
A15: Capex | B15: 0.035 | C15: % of revenue | D15: estimated | E15: Quattro stabilimenti con lavorazioni meccaniche e collaudi richiedono capex di mantenimento medio, centro del range 2,5-5%.
A16: D&A | B16: 0.035 | C16: % of revenue | D16: estimated | E16: Allineato al capex per un business manifatturiero a regime, nel range 2,5-4,5%.
A17: Increase in NWC | B17: 0.22 | C17: % of revenue growth | D17: estimated | E17: Commesse lunghe, scorte di fusioni/forgiati e crediti verso EPC comportano un assorbimento di circolante elevato, parte alta del range 10-25%.
A19: Financing
A20: Total debt at entry | B20: 4.5 | C20: x EBITDA | D20: estimated | E20: Parte medio-bassa del range industrials (4-5,5x) per la ciclicità dell'esposizione oil&gas e la natura a commessa dei ricavi.
A21: of which Senior Term Loan | B21: 3.25 | C21: x EBITDA | D21: estimated | E21: Circa il 72% della leva totale in Term Loan, con il resto in subordinato: struttura standard per un mid-market italiano da ~45 milioni di EBITDA.
A22: Term Loan interest rate | B22: 0.065 | C22: % | D22: estimated | E22: EURIBOR 2,0% più margine ~450bps, coerente con un emittente mid-market ciclico italiano.
A23: Term Loan mandatory amortization | B23: 0.05 | C23: % of original p.a. | D23: estimated | E23: Ammortamento del 5% annuo del nominale, tipico per un term loan amortizing bancario italiano.
A24: Cash sweep on Term Loan | B24: 0.75 | C24: % of surplus cash | D24: estimated | E24: Sweep del 75% del free cash flow eccedente, standard di mercato per strutture bancarie mid-market.
A25: Subordinated Notes interest rate (bullet) | B25: 0.105 | C25: % | D25: estimated | E25: Circa 400bps sopra il senior, in linea con debito subordinato/mezzanino per emittenti industriali ciclici.
A26: RCF commitment (undrawn at close) | B26: 22 | C26: EUR mm | D26: estimated | E26: Circa 0,5x EBITDA, necessario per finanziare i picchi di circolante legati alle commesse.
A27: RCF interest rate | B27: 0.06 | C27: % | D27: estimated | E27: Prezzo leggermente inferiore al term loan, coerente con linee revolving garantite.
A29: Tax and cash
A30: Tax rate (no loss carry-forward) | B30: 0.28 | C30: % | D30: estimated | E30: Aliquota statutaria italiana IRES 24% più IRAP ~3,9%.
A31: Minimum cash (funded at close, never swept) | B31: 6.4 | C31: EUR mm | D31: estimated | E31: Pari al 2% dei ricavi, cassa operativa minima per un gruppo manifatturiero multi-sito.
A33: Exit
A34: Holding period | B34: 5 | C34: years | D34: estimated | E34: Holding period standard di 5 anni, necessario per attraversare il ciclo oil&gas e consolidare l'after-market.
A35: Exit EV / EBITDA | B35: 7.5 | C35: x | D35: estimated | E35: Mezzo turn sotto l'ingresso per prudenza sul base case, data la ciclicità della domanda finale.

Sheet LBO
A1: Progetto Valvole Italia — LBO model (EUR mm)
A2: Every figure is a live formula driven by the Assumptions sheet. Interest on opening balances (no circularity). Greyed columns fall outside the holding period.
A3: Model checks | C3: =IF(AND(ABS(C16)<0.001,MAX($D$67:$M$67)<0.001),"OK","ERROR") | E3: MOIC | F3: =C80 | G3: IRR | H3: =C81
A5: Sources & Uses | C5: EUR mm | D5: x EBITDA | E5: % of total
A6: LTM EBITDA at entry | C6: =Assumptions!$B$8
A7: Entry EV / EBITDA | C7: =Assumptions!$B$10
A8: Purchase of enterprise value | C8: =C6*C7 | D8: =C8/$C$6 | E8: =C8/$C$10
A9: Minimum cash funding | C9: =Assumptions!$B$31 | D9: =C9/$C$6 | E9: =C9/$C$10
A10: Total uses | C10: =C8+C9 | D10: =C10/$C$6 | E10: =C10/$C$10
A12: Senior Term Loan | C12: =C6*Assumptions!$B$21 | D12: =C12/$C$6 | E12: =C12/$C$10
A13: Subordinated Notes | C13: =C6*(Assumptions!$B$20-Assumptions!$B$21) | D13: =C13/$C$6 | E13: =C13/$C$10
A14: Sponsor equity (plug) | C14: =C10-C12-C13 | D14: =C14/$C$6 | E14: =C14/$C$10
A15: Total sources | C15: =SUM(C12:C14) | D15: =C15/$C$6 | E15: =C15/$C$10
A16: Check: sources - uses | C16: =C15-C10
A18: EUR mm | C18: 0 | D18: =C18+1 | E18: =D18+1 | F18: =E18+1 | G18: =F18+1 | H18: =G18+1 | I18: =H18+1 | J18: =I18+1 | K18: =J18+1 | ... M18: =L18+1
A19: In holding period | D19: =IF(D18<=Assumptions!$B$34,1,0) | E19: =IF(E18<=Assumptions!$B$34,1,0) | F19: =IF(F18<=Assumptions!$B$34,1,0) | G19: =IF(G18<=Assumptions!$B$34,1,0) | H19: =IF(H18<=Assumptions!$B$34,1,0) | I19: =IF(I18<=Assumptions!$B$34,1,0) | J19: =IF(J18<=Assumptions!$B$34,1,0) | K19: =IF(K18<=Assumptions!$B$34,1,0) | ... M19: =IF(M18<=Assumptions!$B$34,1,0)
A20: Income statement
A21: Revenue | C21: =Assumptions!$B$7 | D21: =C21*(1+Assumptions!$B$14) | E21: =D21*(1+Assumptions!$B$14) | F21: =E21*(1+Assumptions!$B$14) | G21: =F21*(1+Assumptions!$B$14) | H21: =G21*(1+Assumptions!$B$14) | I21: =H21*(1+Assumptions!$B$14) | J21: =I21*(1+Assumptions!$B$14) | K21: =J21*(1+Assumptions!$B$14) | ... M21: =L21*(1+Assumptions!$B$14)
A22: growth | D22: =D21/C21-1 | E22: =E21/D21-1 | F22: =F21/E21-1 | G22: =G21/F21-1 | H22: =H21/G21-1 | I22: =I21/H21-1 | J22: =J21/I21-1 | K22: =K21/J21-1 | ... M22: =M21/L21-1
A23: EBITDA | C23: =Assumptions!$B$8 | D23: =D21*Assumptions!$B$13 | E23: =E21*Assumptions!$B$13 | F23: =F21*Assumptions!$B$13 | G23: =G21*Assumptions!$B$13 | H23: =H21*Assumptions!$B$13 | I23: =I21*Assumptions!$B$13 | J23: =J21*Assumptions!$B$13 | K23: =K21*Assumptions!$B$13 | ... M23: =M21*Assumptions!$B$13
A24: margin | C24: =C23/C21 | D24: =D23/D21 | E24: =E23/E21 | F24: =F23/F21 | G24: =G23/G21 | H24: =H23/H21 | I24: =I23/I21 | J24: =J23/J21 | ... M24: =M23/M21
A25: Less: D&A | D25: =D21*Assumptions!$B$16 | E25: =E21*Assumptions!$B$16 | F25: =F21*Assumptions!$B$16 | G25: =G21*Assumptions!$B$16 | H25: =H21*Assumptions!$B$16 | I25: =I21*Assumptions!$B$16 | J25: =J21*Assumptions!$B$16 | K25: =K21*Assumptions!$B$16 | ... M25: =M21*Assumptions!$B$16
A26: EBIT | D26: =D23-D25 | E26: =E23-E25 | F26: =F23-F25 | G26: =G23-G25 | H26: =H23-H25 | I26: =I23-I25 | J26: =J23-J25 | K26: =K23-K25 | ... M26: =M23-M25
A27: Less: interest on Term Loan (opening balance) | D27: =C53*Assumptions!$B$22 | E27: =D53*Assumptions!$B$22 | F27: =E53*Assumptions!$B$22 | G27: =F53*Assumptions!$B$22 | H27: =G53*Assumptions!$B$22 | I27: =H53*Assumptions!$B$22 | J27: =I53*Assumptions!$B$22 | K27: =J53*Assumptions!$B$22 | ... M27: =L53*Assumptions!$B$22
A28: Less: interest on Sub Notes (opening balance) | D28: =C54*Assumptions!$B$25 | E28: =D54*Assumptions!$B$25 | F28: =E54*Assumptions!$B$25 | G28: =F54*Assumptions!$B$25 | H28: =G54*Assumptions!$B$25 | I28: =H54*Assumptions!$B$25 | J28: =I54*Assumptions!$B$25 | K28: =J54*Assumptions!$B$25 | ... M28: =L54*Assumptions!$B$25
A29: Less: interest on RCF (opening balance) | D29: =C58*Assumptions!$B$27 | E29: =D58*Assumptions!$B$27 | F29: =E58*Assumptions!$B$27 | G29: =F58*Assumptions!$B$27 | H29: =G58*Assumptions!$B$27 | I29: =H58*Assumptions!$B$27 | J29: =I58*Assumptions!$B$27 | K29: =J58*Assumptions!$B$27 | ... M29: =L58*Assumptions!$B$27
A30: Total interest expense | D30: =SUM(D27:D29) | E30: =SUM(E27:E29) | F30: =SUM(F27:F29) | G30: =SUM(G27:G29) | H30: =SUM(H27:H29) | I30: =SUM(I27:I29) | J30: =SUM(J27:J29) | K30: =SUM(K27:K29) | ... M30: =SUM(M27:M29)
A31: EBT | D31: =D26-D30 | E31: =E26-E30 | F31: =F26-F30 | G31: =G26-G30 | H31: =H26-H30 | I31: =I26-I30 | J31: =J26-J30 | K31: =K26-K30 | ... M31: =M26-M30
A32: Less: tax (none on losses) | D32: =MAX(D31,0)*Assumptions!$B$30 | E32: =MAX(E31,0)*Assumptions!$B$30 | F32: =MAX(F31,0)*Assumptions!$B$30 | G32: =MAX(G31,0)*Assumptions!$B$30 | H32: =MAX(H31,0)*Assumptions!$B$30 | I32: =MAX(I31,0)*Assumptions!$B$30 | J32: =MAX(J31,0)*Assumptions!$B$30 | K32: =MAX(K31,0)*Assumptions!$B$30 | ... M32: =MAX(M31,0)*Assumptions!$B$30
A33: Net income | D33: =D31-D32 | E33: =E31-E32 | F33: =F31-F32 | G33: =G31-G32 | H33: =H31-H32 | I33: =I31-I32 | J33: =J31-J32 | K33: =K31-K32 | ... M33: =M31-M32
A34: Free cash flow
A35: Net income | D35: =D33 | E35: =E33 | F35: =F33 | G35: =G33 | H35: =H33 | I35: =I33 | J35: =J33 | K35: =K33 | ... M35: =M33
A36: Plus: D&A | D36: =D25 | E36: =E25 | F36: =F25 | G36: =G25 | H36: =H25 | I36: =I25 | J36: =J25 | K36: =K25 | ... M36: =M25
A37: Less: capex | D37: =D21*Assumptions!$B$15 | E37: =E21*Assumptions!$B$15 | F37: =F21*Assumptions!$B$15 | G37: =G21*Assumptions!$B$15 | H37: =H21*Assumptions!$B$15 | I37: =I21*Assumptions!$B$15 | J37: =J21*Assumptions!$B$15 | K37: =K21*Assumptions!$B$15 | ... M37: =M21*Assumptions!$B$15
A38: Less: increase in NWC | D38: =(D21-C21)*Assumptions!$B$17 | E38: =(E21-D21)*Assumptions!$B$17 | F38: =(F21-E21)*Assumptions!$B$17 | G38: =(G21-F21)*Assumptions!$B$17 | H38: =(H21-G21)*Assumptions!$B$17 | I38: =(I21-H21)*Assumptions!$B$17 | J38: =(J21-I21)*Assumptions!$B$17 | K38: =(K21-J21)*Assumptions!$B$17 | ... M38: =(M21-L21)*Assumptions!$B$17
A39: Free cash flow | D39: =D35+D36-D37-D38 | E39: =E35+E36-E37-E38 | F39: =F35+F36-F37-F38 | G39: =G35+G36-G37-G38 | H39: =H35+H36-H37-H38 | I39: =I35+I36-I37-I38 | J39: =J35+J36-J37-J38 | K39: =K35+K36-K37-K38 | ... M39: =M35+M36-M37-M38
A40: Cash waterfall
A41: Cash above minimum, opening | D41: =C60-Assumptions!$B$31 | E41: =D60-Assumptions!$B$31 | F41: =E60-Assumptions!$B$31 | G41: =F60-Assumptions!$B$31 | H41: =G60-Assumptions!$B$31 | I41: =H60-Assumptions!$B$31 | J41: =I60-Assumptions!$B$31 | K41: =J60-Assumptions!$B$31 | ... M41: =L60-Assumptions!$B$31
A42: Plus: free cash flow | D42: =D39 | E42: =E39 | F42: =F39 | G42: =G39 | H42: =H39 | I42: =I39 | J42: =J39 | K42: =K39 | ... M42: =M39
A43: Less: Term Loan mandatory amortization | D43: =MIN($C$12*Assumptions!$B$23,C53) | E43: =MIN($C$12*Assumptions!$B$23,D53) | F43: =MIN($C$12*Assumptions!$B$23,E53) | G43: =MIN($C$12*Assumptions!$B$23,F53) | H43: =MIN($C$12*Assumptions!$B$23,G53) | I43: =MIN($C$12*Assumptions!$B$23,H53) | J43: =MIN($C$12*Assumptions!$B$23,I53) | K43: =MIN($C$12*Assumptions!$B$23,J53) | ... M43: =MIN($C$12*Assumptions!$B$23,L53)
A44: Cash available after mandatory debt service | D44: =D41+D42-D43 | E44: =E41+E42-E43 | F44: =F41+F42-F43 | G44: =G41+G42-G43 | H44: =H41+H42-H43 | I44: =I41+I42-I43 | J44: =J41+J42-J43 | K44: =K41+K42-K43 | ... M44: =M41+M42-M43
A45: RCF draw (covers a shortfall) | D45: =MAX(-D44,0) | E45: =MAX(-E44,0) | F45: =MAX(-F44,0) | G45: =MAX(-G44,0) | H45: =MAX(-H44,0) | I45: =MAX(-I44,0) | J45: =MAX(-J44,0) | K45: =MAX(-K44,0) | ... M45: =MAX(-M44,0)
A46: RCF repayment (first use of surplus) | D46: =MIN(MAX(D44,0),C58) | E46: =MIN(MAX(E44,0),D58) | F46: =MIN(MAX(F44,0),E58) | G46: =MIN(MAX(G44,0),F58) | H46: =MIN(MAX(H44,0),G58) | I46: =MIN(MAX(I44,0),H58) | J46: =MIN(MAX(J44,0),I58) | K46: =MIN(MAX(K44,0),J58) | ... M46: =MIN(MAX(M44,0),L58)
A47: Term Loan cash sweep | D47: =MIN((MAX(D44,0)-D46)*Assumptions!$B$24,C53-D43) | E47: =MIN((MAX(E44,0)-E46)*Assumptions!$B$24,D53-E43) | F47: =MIN((MAX(F44,0)-F46)*Assumptions!$B$24,E53-F43) | G47: =MIN((MAX(G44,0)-G46)*Assumptions!$B$24,F53-G43) | H47: =MIN((MAX(H44,0)-H46)*Assumptions!$B$24,G53-H43) | I47: =MIN((MAX(I44,0)-I46)*Assumptions!$B$24,H53-I43) | J47: =MIN((MAX(J44,0)-J46)*Assumptions!$B$24,I53-J43) | K47: =MIN((MAX(K44,0)-K46)*Assumptions!$B$24,J53-K43) | ... M47: =MIN((MAX(M44,0)-M46)*Assumptions!$B$24,L53-M43)
A48: Surplus cash retained on balance sheet | D48: =MAX(D44,0)-D46-D47 | E48: =MAX(E44,0)-E46-E47 | F48: =MAX(F44,0)-F46-F47 | G48: =MAX(G44,0)-G46-G47 | H48: =MAX(H44,0)-H46-H47 | I48: =MAX(I44,0)-I46-I47 | J48: =MAX(J44,0)-J46-J47 | K48: =MAX(K44,0)-K46-K47 | ... M48: =MAX(M44,0)-M46-M47
A49: Debt schedule
A50: Term Loan — opening | D50: =C53 | E50: =D53 | F50: =E53 | G50: =F53 | H50: =G53 | I50: =H53 | J50: =I53 | K50: =J53 | ... M50: =L53
A51: mandatory amortization | D51: =-D43 | E51: =-E43 | F51: =-F43 | G51: =-G43 | H51: =-H43 | I51: =-I43 | J51: =-J43 | K51: =-K43 | ... M51: =-M43
A52: cash sweep | D52: =-D47 | E52: =-E47 | F52: =-F47 | G52: =-G47 | H52: =-H47 | I52: =-I47 | J52: =-J47 | K52: =-K47 | ... M52: =-M47
A53: Term Loan — closing | C53: =C12 | D53: =SUM(D50:D52) | E53: =SUM(E50:E52) | F53: =SUM(F50:F52) | G53: =SUM(G50:G52) | H53: =SUM(H50:H52) | I53: =SUM(I50:I52) | J53: =SUM(J50:J52) | K53: =SUM(K50:K52) | ... M53: =SUM(M50:M52)
A54: Subordinated Notes — closing (bullet) | C54: =C13 | D54: =C54 | E54: =D54 | F54: =E54 | G54: =F54 | H54: =G54 | I54: =H54 | J54: =I54 | K54: =J54 | ... M54: =L54
A55: RCF — opening | D55: =C58 | E55: =D58 | F55: =E58 | G55: =F58 | H55: =G58 | I55: =H58 | J55: =I58 | K55: =J58 | ... M55: =L58
A56: draws | D56: =D45 | E56: =E45 | F56: =F45 | G56: =G45 | H56: =H45 | I56: =I45 | J56: =J45 | K56: =K45 | ... M56: =M45
A57: repayments | D57: =-D46 | E57: =-E46 | F57: =-F46 | G57: =-G46 | H57: =-H46 | I57: =-I46 | J57: =-J46 | K57: =-K46 | ... M57: =-M46
A58: RCF — closing | C58: 0 | D58: =SUM(D55:D57) | E58: =SUM(E55:E57) | F58: =SUM(F55:F57) | G58: =SUM(G55:G57) | H58: =SUM(H55:H57) | I58: =SUM(I55:I57) | J58: =SUM(J55:J57) | K58: =SUM(K55:K57) | ... M58: =SUM(M55:M57)
A59: undrawn RCF headroom | D59: =Assumptions!$B$26-D58 | E59: =Assumptions!$B$26-E58 | F59: =Assumptions!$B$26-F58 | G59: =Assumptions!$B$26-G58 | H59: =Assumptions!$B$26-H58 | I59: =Assumptions!$B$26-I58 | J59: =Assumptions!$B$26-J58 | K59: =Assumptions!$B$26-K58 | ... M59: =Assumptions!$B$26-M58
A60: Cash — closing | C60: =Assumptions!$B$31 | D60: =Assumptions!$B$31+D48 | E60: =Assumptions!$B$31+E48 | F60: =Assumptions!$B$31+F48 | G60: =Assumptions!$B$31+G48 | H60: =Assumptions!$B$31+H48 | I60: =Assumptions!$B$31+I48 | J60: =Assumptions!$B$31+J48 | K60: =Assumptions!$B$31+K48 | ... M60: =Assumptions!$B$31+M48
A61: Total debt | C61: =C53+C54+C58 | D61: =D53+D54+D58 | E61: =E53+E54+E58 | F61: =F53+F54+F58 | G61: =G53+G54+G58 | H61: =H53+H54+H58 | I61: =I53+I54+I58 | J61: =J53+J54+J58 | ... M61: =M53+M54+M58
A62: Net debt | C62: =C61-C60 | D62: =D61-D60 | E62: =E61-E60 | F62: =F61-F60 | G62: =G61-G60 | H62: =H61-H60 | I62: =I61-I60 | J62: =J61-J60 | ... M62: =M61-M60
A63: Credit statistics
A64: Total debt / EBITDA | C64: =C61/C23 | D64: =D61/D23 | E64: =E61/E23 | F64: =F61/F23 | G64: =G61/G23 | H64: =H61/H23 | I64: =I61/I23 | J64: =J61/J23 | ... M64: =M61/M23
A65: EBITDA / interest | D65: =IF(D30>0,D23/D30,"n.m.") | E65: =IF(E30>0,E23/E30,"n.m.") | F65: =IF(F30>0,F23/F30,"n.m.") | G65: =IF(G30>0,G23/G30,"n.m.") | H65: =IF(H30>0,H23/H30,"n.m.") | I65: =IF(I30>0,I23/I30,"n.m.") | J65: =IF(J30>0,J23/J30,"n.m.") | K65: =IF(K30>0,K23/K30,"n.m.") | ... M65: =IF(M30>0,M23/M30,"n.m.")
A66: Checks and helpers
A67: Cash conservation |change in net debt - FCF| (must be 0) | D67: =ABS((C62-D62)-D39) | E67: =ABS((D62-E62)-E39) | F67: =ABS((E62-F62)-F39) | G67: =ABS((F62-G62)-G39) | H67: =ABS((G62-H62)-H39) | I67: =ABS((H62-I62)-I39) | J67: =ABS((I62-J62)-J39) | K67: =ABS((J62-K62)-K39) | ... M67: =ABS((L62-M62)-M39)
A68: EBITDA / interest, holding period only | D68: =IF(AND(D19=1,D30>0),D23/D30,"") | E68: =IF(AND(E19=1,E30>0),E23/E30,"") | F68: =IF(AND(F19=1,F30>0),F23/F30,"") | G68: =IF(AND(G19=1,G30>0),G23/G30,"") | H68: =IF(AND(H19=1,H30>0),H23/H30,"") | I68: =IF(AND(I19=1,I30>0),I23/I30,"") | J68: =IF(AND(J19=1,J30>0),J23/J30,"") | K68: =IF(AND(K19=1,K30>0),K23/K30,"") | ... M68: =IF(AND(M19=1,M30>0),M23/M30,"")
A69: RCF balance, holding period only | D69: =D58*D19 | E69: =E58*E19 | F69: =F58*F19 | G69: =G58*G19 | H69: =H58*H19 | I69: =I58*I19 | J69: =J58*J19 | K69: =K58*K19 | ... M69: =M58*M19
A70: Sponsor equity cash flows | C70: =-C14 | D70: =IF(D18=Assumptions!$B$34,$C$78,0) | E70: =IF(E18=Assumptions!$B$34,$C$78,0) | F70: =IF(F18=Assumptions!$B$34,$C$78,0) | G70: =IF(G18=Assumptions!$B$34,$C$78,0) | H70: =IF(H18=Assumptions!$B$34,$C$78,0) | I70: =IF(I18=Assumptions!$B$34,$C$78,0) | J70: =IF(J18=Assumptions!$B$34,$C$78,0) | K70: =IF(K18=Assumptions!$B$34,$C$78,0) | ... M70: =IF(M18=Assumptions!$B$34,$C$78,0)
A72: Returns | C72: EUR mm
A73: Holding period (years) | C73: =Assumptions!$B$34
A74: Exit EBITDA (final year of hold) | C74: =INDEX($D$23:$M$23,C73)
A75: Exit EV / EBITDA | C75: =Assumptions!$B$35
A76: Exit enterprise value | C76: =C74*C75
A77: Less: net debt at exit | C77: =INDEX($D$62:$M$62,C73)
A78: Exit equity value | C78: =C76-C77
A79: Entry sponsor equity | C79: =C14
A80: MOIC | C80: =C78/C79
A81: IRR (= MOIC ^ (1 / years) - 1: no interim dividends) | C81: =IF(C80>0,C80^(1/C73)-1,-1)
A82: IRR cross-check: Excel IRR() on equity cash flows | C82: =IFERROR(IRR(C70:M70),"n.m.")
A83: Peak RCF draw during hold | C83: =MAX($D$69:$M$69)
A84: Minimum EBITDA / interest during hold | C84: =IF(COUNT($D$68:$M$68)>0,MIN($D$68:$M$68),"n.m.")
A85: Liquidity flag | C85: =IF(C83>Assumptions!$B$26+0.000001,"RCF over commitment: structure does not fund itself",IF(C83>0,"RCF drawn to cover a shortfall","-"))
A86: Coverage flag | C86: =IF(AND(ISNUMBER(C84),C84<2),"Coverage below 2.0x","-")
A87: Equity flag | C87: =IF(C78<=0,"Exit equity <= 0","-")
A89: IRR sensitivity: exit multiple (rows) x holding period (columns)
A90: Change vs base exit multiple | exit multiple | holding period (years): | D90: 3 | E90: 4 | F90: 5 | G90: 6 | H90: 7
B91: -1 | C91: =$C$75+B91 | D91: =IFERROR(IF((INDEX($D$23:$M$23,D$90)*$C91-INDEX($D$62:$M$62,D$90))>0,((INDEX($D$23:$M$23,D$90)*$C91-INDEX($D$62:$M$62,D$90))/$C$79)^(1/D$90)-1,-1),"n.a.") | E91: =IFERROR(IF((INDEX($D$23:$M$23,E$90)*$C91-INDEX($D$62:$M$62,E$90))>0,((INDEX($D$23:$M$23,E$90)*$C91-INDEX($D$62:$M$62,E$90))/$C$79)^(1/E$90)-1,-1),"n.a.") | F91: =IFERROR(IF((INDEX($D$23:$M$23,F$90)*$C91-INDEX($D$62:$M$62,F$90))>0,((INDEX($D$23:$M$23,F$90)*$C91-INDEX($D$62:$M$62,F$90))/$C$79)^(1/F$90)-1,-1),"n.a.") | G91: =IFERROR(IF((INDEX($D$23:$M$23,G$90)*$C91-INDEX($D$62:$M$62,G$90))>0,((INDEX($D$23:$M$23,G$90)*$C91-INDEX($D$62:$M$62,G$90))/$C$79)^(1/G$90)-1,-1),"n.a.") | H91: =IFERROR(IF((INDEX($D$23:$M$23,H$90)*$C91-INDEX($D$62:$M$62,H$90))>0,((INDEX($D$23:$M$23,H$90)*$C91-INDEX($D$62:$M$62,H$90))/$C$79)^(1/H$90)-1,-1),"n.a.")
B92: -0.5 | C92: =$C$75+B92 | D92: =IFERROR(IF((INDEX($D$23:$M$23,D$90)*$C92-INDEX($D$62:$M$62,D$90))>0,((INDEX($D$23:$M$23,D$90)*$C92-INDEX($D$62:$M$62,D$90))/$C$79)^(1/D$90)-1,-1),"n.a.") | E92: =IFERROR(IF((INDEX($D$23:$M$23,E$90)*$C92-INDEX($D$62:$M$62,E$90))>0,((INDEX($D$23:$M$23,E$90)*$C92-INDEX($D$62:$M$62,E$90))/$C$79)^(1/E$90)-1,-1),"n.a.") | F92: =IFERROR(IF((INDEX($D$23:$M$23,F$90)*$C92-INDEX($D$62:$M$62,F$90))>0,((INDEX($D$23:$M$23,F$90)*$C92-INDEX($D$62:$M$62,F$90))/$C$79)^(1/F$90)-1,-1),"n.a.") | G92: =IFERROR(IF((INDEX($D$23:$M$23,G$90)*$C92-INDEX($D$62:$M$62,G$90))>0,((INDEX($D$23:$M$23,G$90)*$C92-INDEX($D$62:$M$62,G$90))/$C$79)^(1/G$90)-1,-1),"n.a.") | H92: =IFERROR(IF((INDEX($D$23:$M$23,H$90)*$C92-INDEX($D$62:$M$62,H$90))>0,((INDEX($D$23:$M$23,H$90)*$C92-INDEX($D$62:$M$62,H$90))/$C$79)^(1/H$90)-1,-1),"n.a.")
B93: 0 | C93: =$C$75+B93 | D93: =IFERROR(IF((INDEX($D$23:$M$23,D$90)*$C93-INDEX($D$62:$M$62,D$90))>0,((INDEX($D$23:$M$23,D$90)*$C93-INDEX($D$62:$M$62,D$90))/$C$79)^(1/D$90)-1,-1),"n.a.") | E93: =IFERROR(IF((INDEX($D$23:$M$23,E$90)*$C93-INDEX($D$62:$M$62,E$90))>0,((INDEX($D$23:$M$23,E$90)*$C93-INDEX($D$62:$M$62,E$90))/$C$79)^(1/E$90)-1,-1),"n.a.") | F93: =IFERROR(IF((INDEX($D$23:$M$23,F$90)*$C93-INDEX($D$62:$M$62,F$90))>0,((INDEX($D$23:$M$23,F$90)*$C93-INDEX($D$62:$M$62,F$90))/$C$79)^(1/F$90)-1,-1),"n.a.") | G93: =IFERROR(IF((INDEX($D$23:$M$23,G$90)*$C93-INDEX($D$62:$M$62,G$90))>0,((INDEX($D$23:$M$23,G$90)*$C93-INDEX($D$62:$M$62,G$90))/$C$79)^(1/G$90)-1,-1),"n.a.") | H93: =IFERROR(IF((INDEX($D$23:$M$23,H$90)*$C93-INDEX($D$62:$M$62,H$90))>0,((INDEX($D$23:$M$23,H$90)*$C93-INDEX($D$62:$M$62,H$90))/$C$79)^(1/H$90)-1,-1),"n.a.")
B94: 0.5 | C94: =$C$75+B94 | D94: =IFERROR(IF((INDEX($D$23:$M$23,D$90)*$C94-INDEX($D$62:$M$62,D$90))>0,((INDEX($D$23:$M$23,D$90)*$C94-INDEX($D$62:$M$62,D$90))/$C$79)^(1/D$90)-1,-1),"n.a.") | E94: =IFERROR(IF((INDEX($D$23:$M$23,E$90)*$C94-INDEX($D$62:$M$62,E$90))>0,((INDEX($D$23:$M$23,E$90)*$C94-INDEX($D$62:$M$62,E$90))/$C$79)^(1/E$90)-1,-1),"n.a.") | F94: =IFERROR(IF((INDEX($D$23:$M$23,F$90)*$C94-INDEX($D$62:$M$62,F$90))>0,((INDEX($D$23:$M$23,F$90)*$C94-INDEX($D$62:$M$62,F$90))/$C$79)^(1/F$90)-1,-1),"n.a.") | G94: =IFERROR(IF((INDEX($D$23:$M$23,G$90)*$C94-INDEX($D$62:$M$62,G$90))>0,((INDEX($D$23:$M$23,G$90)*$C94-INDEX($D$62:$M$62,G$90))/$C$79)^(1/G$90)-1,-1),"n.a.") | H94: =IFERROR(IF((INDEX($D$23:$M$23,H$90)*$C94-INDEX($D$62:$M$62,H$90))>0,((INDEX($D$23:$M$23,H$90)*$C94-INDEX($D$62:$M$62,H$90))/$C$79)^(1/H$90)-1,-1),"n.a.")
B95: 1 | C95: =$C$75+B95 | D95: =IFERROR(IF((INDEX($D$23:$M$23,D$90)*$C95-INDEX($D$62:$M$62,D$90))>0,((INDEX($D$23:$M$23,D$90)*$C95-INDEX($D$62:$M$62,D$90))/$C$79)^(1/D$90)-1,-1),"n.a.") | E95: =IFERROR(IF((INDEX($D$23:$M$23,E$90)*$C95-INDEX($D$62:$M$62,E$90))>0,((INDEX($D$23:$M$23,E$90)*$C95-INDEX($D$62:$M$62,E$90))/$C$79)^(1/E$90)-1,-1),"n.a.") | F95: =IFERROR(IF((INDEX($D$23:$M$23,F$90)*$C95-INDEX($D$62:$M$62,F$90))>0,((INDEX($D$23:$M$23,F$90)*$C95-INDEX($D$62:$M$62,F$90))/$C$79)^(1/F$90)-1,-1),"n.a.") | G95: =IFERROR(IF((INDEX($D$23:$M$23,G$90)*$C95-INDEX($D$62:$M$62,G$90))>0,((INDEX($D$23:$M$23,G$90)*$C95-INDEX($D$62:$M$62,G$90))/$C$79)^(1/G$90)-1,-1),"n.a.") | H95: =IFERROR(IF((INDEX($D$23:$M$23,H$90)*$C95-INDEX($D$62:$M$62,H$90))>0,((INDEX($D$23:$M$23,H$90)*$C95-INDEX($D$62:$M$62,H$90))/$C$79)^(1/H$90)-1,-1),"n.a.")

Sheet Audit
A1: Progetto Valvole Italia — audit trail
A2: Exported 2026-09-23 · figures in EUR mm
A5: Python engine snapshot at export vs live workbook
A6: Metric | B6: Engine (static) | C6: Live workbook | status
A7: Exit equity value | B7: 265.88024 | C7: =LBO!$C$78
A8: MOIC | B8: 1.6291681 | C8: =LBO!$C$80
A9: IRR | B9: 0.10253702 | C9: =LBO!$C$81
A10: Status | C10: =IF(ABS(C8-B8)<0.000001,"Matches the Python engine","Inputs changed since export: engine snapshot no longer applies")
A12: Sector call (Claude)
A13: Sector | C13: Industrials / manufacturing
A14: Rationale | C14: Produttore manifatturiero italiano di valvole industriali con 4 stabilimenti, destinate a oil&gas e utilities: classico industrial mid-market ciclico.
A16: Guardrail adjustments to Claude's proposal
C17: None: every estimate was inside the benchmark ranges
A19: Guardrail warnings
C20: None
A22: Key risks to underwrite
C23: Ciclicità degli investimenti oil&gas: un rallentamento del capex dei clienti finali comprime volumi e assorbe circolante.
C24: Concentrazione su pochi clienti EPC/utilities e rischio di gare a prezzo con erosione dei margini.
C25: Volatilità dei costi di fusioni, forgiati e acciai speciali, con difficoltà di ribaltamento su contratti a prezzo fisso.
C26: Assorbimento di capitale circolante elevato su commesse lunghe, che riduce la capacità di cash sweep.
C27: Rischio di esecuzione/qualità e costi di riorganizzazione su quattro stabilimenti potenzialmente sotto-utilizzati.
A29: Modelling conventions
C30: Interest on opening balances of every tranche: no circular reference, no iterative calculation.
C31: Cash waterfall: FCF + opening surplus cash -> Term Loan mandatory amortization -> shortfall drawn on RCF / surplus repays RCF first, then sweeps the Term Loan -> remainder kept as cash.
C32: Subordinated Notes are bullet and non-call: repaid at exit out of the equity value.
C33: Exit: final-year EBITDA x exit multiple, less net debt (Term Loan + Sub Notes + RCF - cash).
C34: Not modelled: transaction fees / OID, interest income on cash, RCF commitment fee, tax-loss carry-forwards, dividends / recaps, management equity.
C35: Only two equity cash flows, so IRR = MOIC ^ (1 / years) - 1; Excel IRR() is shown as a cross-check.
